[{"name": "Nutty Irishman Coffee", "size": 1, "id": 110488, "ingredients": ["Baileys Irish Cream"], "directions": ["Fill cup with (6 oz.) coffee.", "Add (1oz.) Baileys.", "Add (1oz.) Frangelico.", "Top with whipped cream."], "category": "Beverages", "similar": [{"id": 184346, "name": "Nutty Irishman Coffee With a Kick!!!!"}, {"id": 346904, "name": "Irish Whiskey Cream Liqueur Coffee"}, {"id": 199533, "name": "Buttery Bailey's Nog"}, {"id": 407442, "name": "Chocolatey Irish Coffee"}, {"id": 303712, "name": "After Eight Shooter"}]}, {"name": "Boston Cream Pie Martini", "size": 1, "id": 150063, "ingredients": ["vanilla vodka", "Baileys Irish Cream"], "directions": ["mix and chill for 30 minute."], "category": "Beverages", "similar": [{"id": 314121, "name": "Want S'more Martinis?"}, {"id": 262766, "name": "Cherry Bomb Martini !"}, {"id": 263402, "name": "Wedding Cake Martini II"}, {"id": 164176, "name": "Sweet Chocolate Raspberry Martini"}, {"id": 473113, "name": "Cake Batter Martini"}]}, {"name": "Sweet Chocolate Raspberry Martini", "size": 1, "id": 164176, "ingredients": ["vodka", "chocolate"], "directions": ["Place rim of chilled glass into rasperry preserves.", "Fill a cocktail shaker with ice. Add the chocolate liqueur, raspberry preserves and vodka to the shaker.", "Shake briskly to mix and chill.", "Strain into the martini glass. Garnish with the chocolate."], "category": "Beverages", "similar": [{"id": 457273, "name": "Chocolate Caramel Martini"}, {"id": 309491, "name": "Chocolate Covered Cherry Martini"}, {"id": 473113, "name": "Cake Batter Martini"}, {"id": 150063, "name": "Boston Cream Pie Martini"}, {"id": 262766, "name": "Cherry Bomb Martini !"}]}, {"name": "Saharan Martini", "size": 1, "id": 173566, "ingredients": ["Amarula cream liqueur", "vodka"], "directions": ["Add all ingredients to a cocktail shaker filled with ice and shake for about 30 seconds.", "Strain into martini glass and sprinkle chocolate curls on top."], "category": "Beverages", "similar": [{"id": 185518, "name": "Madagascar Vanilla Martini"}, {"id": 220201, "name": "Amalyser"}, {"id": 263402, "name": "Wedding Cake Martini II"}, {"id": 185025, "name": "Caramel Delight"}, {"id": 457273, "name": "Chocolate Caramel Martini"}]}, {"name": "Nutty Irishman Coffee With a Kick!!!!", "size": 1, "id": 184346, "ingredients": ["Baileys Irish Cream", "Kahlua", "cinnamon"], "directions": ["Fill large coffee mug with", "Baileys, Frangelico and Kaluha top with coffee.", "Garnish with whipped cream and sprinkle with cinnamon."], "category": "Beverages", "similar": [{"id": 110488, "name": "Nutty Irishman Coffee"}, {"id": 346904, "name": "Irish Whiskey Cream Liqueur Coffee"}, {"id": 407442, "name": "Chocolatey Irish Coffee"}, {"id": 199533, "name": "Buttery Bailey's Nog"}, {"id": 216594, "name": "Irish Flag Layered Shot"}]}, {"name": "Caramel Delight", "size": 1, "id": 185025, "ingredients": ["Amarula cream liqueur", "vodka"], "directions": ["Coat the rim of two chilled martini glasses with caramel dip into cinnamon and sugar mixture then drizzle the caramel and chocolate inside the glass.", "In a shaker add the first 3 ingredients with a 12 of ice cubes. Give a really good shake.", "Pour into prepared glasses with or without ice.", "Enjoy!"], "category": "Beverages", "similar": [{"id": 220201, "name": "Amalyser"}, {"id": 220197, "name": "Amarula Colada"}, {"id": 233607, "name": "Amarula Delight"}, {"id": 173566, "name": "Saharan Martini"}, {"id": 185655, "name": "Fruit and Nuts With Cream"}]}, {"name": "Amarula Mint Cream", "size": 1, "id": 185230, "ingredients": ["green creme de menthe", "Amarula cream liqueur", "vanilla ice cream", "milk"], "directions": ["Mix all the ingredients together in a blender with crushed ice."], "category": "Beverages", "similar": [{"id": 233607, "name": "Amarula Delight"}, {"id": 220197, "name": "Amarula Colada"}, {"id": 185655, "name": "Fruit and Nuts With Cream"}, {"id": 185025, "name": "Caramel Delight"}, {"id": 220201, "name": "Amalyser"}]}, {"name": "African Raspberry", "size": 1, "id": 185515, "ingredients": ["Amarula cream liqueur", "Chambord raspberry liquor"], "directions": ["Serve over ice and enjoy."], "category": "Beverages", "similar": [{"id": 189425, "name": "White Chocolate Raspberry Truffle"}, {"id": 220197, "name": "Amarula Colada"}, {"id": 219853, "name": "Nuts and Berries Cocktail"}, {"id": 483263, "name": "Purple Dream"}, {"id": 220201, "name": "Amalyser"}]}, {"name": "Madagascar Vanilla Martini", "size": 1, "id": 185518, "ingredients": ["vanilla vodka", "Amarula cream liqueur", "half-and-half", "heavy whipping cream", "maraschino cherry"], "directions": ["Combine ingredient in a martini shaker filled with ice and shake vigorously.", "Pour into a martini glass and garnish with a cherry. Glass can be rimmed with butterscotch sauce."], "category": "Beverages", "similar": [{"id": 173566, "name": "Saharan Martini"}, {"id": 457273, "name": "Chocolate Caramel Martini"}, {"id": 309491, "name": "Chocolate Covered Cherry Martini"}, {"id": 263402, "name": "Wedding Cake Martini II"}, {"id": 150063, "name": "Boston Cream Pie Martini"}]}, {"name": "Fruit and Nuts With Cream", "size": 1, "id": 185655, "ingredients": ["Grand Marnier", "Amarula cream liqueur"], "directions": ["Dip the rim of a liqueur glass in caramel syrup.", "Layer the ingredients in the order listed.", "Using the back of a spoon to pour over each layer will give you good results."], "category": "Beverages", "similar": [{"id": 185230, "name": "Amarula Mint Cream"}, {"id": 220197, "name": "Amarula Colada"}, {"id": 185025, "name": "Caramel Delight"}, {"id": 233607, "name": "Amarula Delight"}, {"id": 220201, "name": "Amalyser"}]}, {"name": "White Chocolate Raspberry Truffle", "size": 1, "id": 189425, "ingredients": ["Chambord raspberry liquor"], "directions": ["Pour liqueurs over ice.", "Stir.", "Cheers!"], "category": "Beverages", "similar": [{"id": 483263, "name": "Purple Dream"}, {"id": 185515, "name": "African Raspberry"}, {"id": 164176, "name": "Sweet Chocolate Raspberry Martini"}, {"id": 253486, "name": "The Homecoming"}, {"id": 219853, "name": "Nuts and Berries Cocktail"}]}, {"name": "Oatmeal Cookie Cocktail", "size": 1, "id": 190430, "ingredients": ["Baileys Irish Cream"], "directions": ["Add a scoop of ice to your shaker.", "Add ingredients.", "Shake & strain into a glass of ice rimmed with cinnamon."], "category": "Beverages", "similar": [{"id": 261770, "name": "Cookies &amp; Cream Cocktail"}, {"id": 199533, "name": "Buttery Bailey's Nog"}, {"id": 150063, "name": "Boston Cream Pie Martini"}, {"id": 213194, "name": "Skor Bar"}, {"id": 314121, "name": "Want S'more Martinis?"}]}, {"name": "Buttery Bailey's Nog", "size": 1, "id": 199533, "ingredients": ["Baileys Irish Cream"], "directions": ["Pour ingredients into glass.", "Stir.", "May add ice or whip cream if you like.", "Enjoy!"], "category": "Beverages", "similar": [{"id": 110488, "name": "Nutty Irishman Coffee"}, {"id": 303712, "name": "After Eight Shooter"}, {"id": 190430, "name": "Oatmeal Cookie Cocktail"}, {"id": 213194, "name": "Skor Bar"}, {"id": 150063, "name": "Boston Cream Pie Martini"}]}, {"name": "Skor Bar", "size": 1, "id": 213194, "ingredients": ["Kahlua", "Baileys Irish Cream", "Creme de Cacao"], "directions": ["Mix ingredients in an 8 oz. shaker and shake well.", "Serve."], "category": "Beverages", "similar": [{"id": 219677, "name": "Chocolate Milk Shake"}, {"id": 199533, "name": "Buttery Bailey's Nog"}, {"id": 303712, "name": "After Eight Shooter"}, {"id": 110488, "name": "Nutty Irishman Coffee"}, {"id": 190430, "name": "Oatmeal Cookie Cocktail"}]}, {"name": "Lifesaver a Layered Shot", "size": 1, "id": 216589, "ingredients": ["irish cream"], "directions": ["Dip the rim into caramel topping. Layer each of these into a shot glass in the order given.", "The secret is to pour slowly, barely dribble the liqueurs into your glass.", "Start with your first liqueur and pour it into your glass, now take your spoon and place the tip of the spoon very close to your first liqueur, now carefully and slowly pour in your second liqueur over the back of the spoon and into the glass topping with cream."], "category": "Beverages", "similar": [{"id": 219440, "name": "Cookies and Cream a Layered Shot!"}, {"id": 216595, "name": "Irish Monk: Layered Shot"}, {"id": 303712, "name": "After Eight Shooter"}, {"id": 199533, "name": "Buttery Bailey's Nog"}, {"id": 185025, "name": "Caramel Delight"}]}, {"name": "Irish Flag Layered Shot", "size": 1, "id": 216594, "ingredients": ["green creme de menthe", "irish cream", "brandy"], "directions": ["Layer in a pony glass or shot glass in the order given.", "The secret is to pour slowly, barely dribble the liqueurs into your glass.", "Start with your first liqueur and pour it into your glass, now take your spoon and place the tip of the spoon very close to your first liqueur, now carefully and slowly pour in your second liqueur over the back of the spoon and into the glass, then your third."], "category": "Beverages", "similar": [{"id": 216596, "name": "Irish Sunset/Sunrise"}, {"id": 216595, "name": "Irish Monk: Layered Shot"}, {"id": 346904, "name": "Irish Whiskey Cream Liqueur Coffee"}, {"id": 184346, "name": "Nutty Irishman Coffee With a Kick!!!!"}, {"id": 303712, "name": "After Eight Shooter"}]}, {"name": "Irish Monk: Layered Shot", "size": 1, "id": 216595, "ingredients": ["irish cream"], "directions": ["Layer in a pony glass or shot glass in the order given.", "The secret is to pour slowly, barely dribble the liqueurs into your glass.", "Start with your first liqueur and pour it into your glass, now take your spoon and place the tip of the spoon very close to your first liqueur, now carefully and slowly pour in your second liqueur over the back of the spoon and into the glass, then your third."], "category": "Beverages", "similar": [{"id": 216589, "name": "Lifesaver a Layered Shot"}, {"id": 216594, "name": "Irish Flag Layered Shot"}, {"id": 219440, "name": "Cookies and Cream a Layered Shot!"}, {"id": 216596, "name": "Irish Sunset/Sunrise"}, {"id": 346904, "name": "Irish Whiskey Cream Liqueur Coffee"}]}, {"name": "Irish Sunset/Sunrise", "size": 1, "id": 216596, "ingredients": ["Amaretto", "irish cream"], "directions": ["Layer in a shot glass in the order given.", "The secret is to pour slowly, barely dribble the liqueurs into your glass.", "Start with your first liqueur and pour it into your glass, now take your spoon and place the tip of the spoon very close to your first liqueur, now carefully and slowly pour in your second liqueur over the back of the spoon and into the glass, then your third."], "category": "Beverages", "similar": [{"id": 216594, "name": "Irish Flag Layered Shot"}, {"id": 216595, "name": "Irish Monk: Layered Shot"}, {"id": 346904, "name": "Irish Whiskey Cream Liqueur Coffee"}, {"id": 184346, "name": "Nutty Irishman Coffee With a Kick!!!!"}, {"id": 110488, "name": "Nutty Irishman Coffee"}]}, {"name": "Passion Martini", "size": 1, "id": 216763, "ingredients": ["alize red passion liqueur", "Malibu rum", "cranberry juice"], "directions": ["Pour all ingredients into a martini shaker full of ice.  Shake vigorously and strain into a chilled martini glass.  Enjoy!"], "category": "Beverages", "similar": [{"id": 391716, "name": "Malibu Punch"}, {"id": 243096, "name": "Tokyo Tea"}, {"id": 262629, "name": "Spicy Sparkling Cider (Cocktail)"}, {"id": 437561, "name": "Liquid Mari-Jane"}, {"id": 245853, "name": "Absolut Iced Tea"}]}, {"name": "Cookies and Cream a Layered Shot!", "size": 1, "id": 219440, "ingredients": ["Creme de Cacao", "irish cream"], "directions": ["Place chocolate and caramel on to a plate swirl them together.", "Dip the rim of the glass into chocolate and caramel topping.", "Layer each of these into a shot glass in the order given.", "The secret is to pour slowly, barely dribble the liqueurs into your glass.", "Start with your first liqueur and pour it into your glass, now take your spoon and place the tip of the spoon very close to your first liqueur, now carefully and slowly pour in your second liqueur over the BACK of the spoon and into the glass topping with cream."], "category": "Beverages", "similar": [{"id": 216589, "name": "Lifesaver a Layered Shot"}, {"id": 216595, "name": "Irish Monk: Layered Shot"}, {"id": 261770, "name": "Cookies &amp; Cream Cocktail"}, {"id": 190430, "name": "Oatmeal Cookie Cocktail"}, {"id": 303712, "name": "After Eight Shooter"}]}, {"name": "Chocolate Milk Shake", "size": 1, "id": 219677, "ingredients": ["Kahlua", "Amaretto", "Baileys Irish Cream", "vodka", "maraschino cherry"], "directions": ["Fill a pint glass full of ice. Transfer ice into blender and add a couple extra cubes more.", "Add all liquors and blend until smooth and looks like a milkshake. Pour back into pint glass.", "Garnish with whipped cream and a cherry."], "category": "Beverages", "similar": [{"id": 245853, "name": "Absolut Iced Tea"}, {"id": 213194, "name": "Skor Bar"}, {"id": 150063, "name": "Boston Cream Pie Martini"}, {"id": 284793, "name": "Apple Pie and Iced Cream"}, {"id": 219853, "name": "Nuts and Berries Cocktail"}]}, {"name": "Nuts and Berries Cocktail", "size": 1, "id": 219853, "ingredients": ["Absolut kurant vodka", "Chambord raspberry liquor", "amaretto liqueur", "half-and-half"], "directions": ["Fill metal shaker with ice and add all ingredients. Shake until outside of the shaker is frosty. Strain into a snifter. For garnish you can add a little whipped cream and drizzle a little chambord over the top.", "Perfect drink for a dessert. It tastes a lot like a milkshake though so be careful -- they go down quick!"], "category": "Beverages", "similar": [{"id": 185515, "name": "African Raspberry"}, {"id": 391716, "name": "Malibu Punch"}, {"id": 219677, "name": "Chocolate Milk Shake"}, {"id": 221196, "name": "Pralines and Cream Cocktail"}, {"id": 245853, "name": "Absolut Iced Tea"}]}, {"name": "Amarula Colada", "size": 1, "id": 220197, "ingredients": ["Amarula cream liqueur", "white rum", "coconut cream"], "directions": ["Blend all ingredients with crushed ice and pour into a tall cocktail glass.", "Garnish with pineapple slice and cherry."], "category": "Beverages", "similar": [{"id": 233607, "name": "Amarula Delight"}, {"id": 220618, "name": "Landslide"}, {"id": 220201, "name": "Amalyser"}, {"id": 185230, "name": "Amarula Mint Cream"}, {"id": 185515, "name": "African Raspberry"}]}, {"name": "Amalyser", "size": 1, "id": 220201, "ingredients": ["Amarula cream liqueur", "vodka"], "directions": ["Shake ingredients and strain into a tall glass filled with ice.", "Top up with coke."], "category": "Beverages", "similar": [{"id": 185025, "name": "Caramel Delight"}, {"id": 220197, "name": "Amarula Colada"}, {"id": 233607, "name": "Amarula Delight"}, {"id": 185515, "name": "African Raspberry"}, {"id": 173566, "name": "Saharan Martini"}]}, {"name": "Landslide", "size": 1, "id": 220618, "ingredients": ["Amaretto", "Amarula cream liqueur"], "directions": ["Layer the ingredients in the shot glass in the following order: Crème de Bananes, Disaronno Amaretto, Amarula Cream.", "Enjoy!  ;)."], "category": "Beverages", "similar": [{"id": 233607, "name": "Amarula Delight"}, {"id": 220197, "name": "Amarula Colada"}, {"id": 185515, "name": "African Raspberry"}, {"id": 220201, "name": "Amalyser"}, {"id": 391716, "name": "Malibu Punch"}]}, {"name": "Pralines and Cream Cocktail", "size": 1, "id": 221196, "ingredients": ["vanilla ice cream", "vanilla vodka", "Amaretto", "pecans"], "directions": ["Add all ingredients expect the pecans into a blender and blend until smooth.", "Pour into a snifter and garnish with a dollop of whipped cream and pecan pieces.", "Serve with a straw and a spoon. They're quite thick."], "category": "Beverages", "similar": [{"id": 284793, "name": "Apple Pie and Iced Cream"}, {"id": 219853, "name": "Nuts and Berries Cocktail"}, {"id": 150063, "name": "Boston Cream Pie Martini"}, {"id": 185518, "name": "Madagascar Vanilla Martini"}, {"id": 164176, "name": "Sweet Chocolate Raspberry Martini"}]}, {"name": "Amarula Delight", "size": 1, "id": 233607, "ingredients": ["Amarula cream liqueur"], "directions": ["Add Amarula and Frangelico into a shaker with ice and shake about 15 times.", "Strain into a champagne flutes or martini glass.", "Take a sharp knife and make a small slit into the truffle and press onto the rim off the glass."], "category": "Beverages", "similar": [{"id": 220618, "name": "Landslide"}, {"id": 220197, "name": "Amarula Colada"}, {"id": 185230, "name": "Amarula Mint Cream"}, {"id": 220201, "name": "Amalyser"}, {"id": 185515, "name": "African Raspberry"}]}, {"name": "Tokyo Tea", "size": 1, "id": 243096, "ingredients": ["citrus-infused vodka", "light rum", "lemon wedge", "lime wedge", "maraschino cherry"], "directions": ["Fill pint or tall glass with ice, add vodka, gin, rum, midori and sweet and sour. Stir with cockail stirrer and float 1/2 7-up on top. Garnish with lemon, lime and cherry.", "I think they look really cute with little umbrellas."], "category": "Beverages", "similar": [{"id": 245853, "name": "Absolut Iced Tea"}, {"id": 391716, "name": "Malibu Punch"}, {"id": 216763, "name": "Passion Martini"}, {"id": 262629, "name": "Spicy Sparkling Cider (Cocktail)"}, {"id": 437561, "name": "Liquid Mari-Jane"}]}, {"name": "Absolut Iced Tea", "size": 1, "id": 245853, "ingredients": ["Absolut vodka", "peach vodka", "Absolut citron vodka", "Absolut mandarin vodka", "triple sec", "lemon wedge", "lime wedge", "maraschino cherry"], "directions": ["Fill pint or any large 16 oz glass full of ice. Add vodkas, triple sec, sweet & sour and cola.", "Lightly stir with a cocktail stirrer or straw.", "Garnish with lemon, lime and maraschino cherry."], "category": "Beverages", "similar": [{"id": 243096, "name": "Tokyo Tea"}, {"id": 219677, "name": "Chocolate Milk Shake"}, {"id": 391716, "name": "Malibu Punch"}, {"id": 219853, "name": "Nuts and Berries Cocktail"}, {"id": 216763, "name": "Passion Martini"}]}, {"name": "The Homecoming", "size": 1, "id": 253486, "ingredients": ["raspberry vodka", "cranberry juice", "frozen raspberries"], "directions": ["Pour the first 3 ingredients into a flute (watch the bubbles on the champagne) and add raspberries (they act as ice)."], "category": "Beverages", "similar": [{"id": 355188, "name": "The Love Potion"}, {"id": 284793, "name": "Apple Pie and Iced Cream"}, {"id": 189425, "name": "White Chocolate Raspberry Truffle"}, {"id": 348151, "name": "Pama and Circumstance"}, {"id": 185515, "name": "African Raspberry"}]}, {"name": "Cookies &amp; Cream Cocktail", "size": 1, "id": 261770, "ingredients": ["milk", "ice cream", "Baileys Irish Cream", "Kahlua", "honey", "strawberry"], "directions": ["Add milk, ice cream, Baileys and Kahlua to crushed cookies and blend until well combined.", "DRIZZLE honey on the inside of two cocktail glasses. Pour cocktail into each glass and serve garnished with strawberries."], "category": "Beverages", "similar": [{"id": 190430, "name": "Oatmeal Cookie Cocktail"}, {"id": 150063, "name": "Boston Cream Pie Martini"}, {"id": 314121, "name": "Want S'more Martinis?"}, {"id": 213194, "name": "Skor Bar"}, {"id": 219677, "name": "Chocolate Milk Shake"}]}, {"name": "Spicy Sparkling Cider (Cocktail)", "size": 1, "id": 262629, "ingredients": ["spiced rum", "dark rum", "sparkling apple cider", "ground cinnamon", "sugar", "lemon juice", "lime juice"], "directions": ["Combined sugar and cinnamon well. Wet glass with lemon or lime juice and dip rim into cinnamon sugar mixture.", "Fill highball or chimney glass with ice. Add spiced rum, dark rum. Add sparkling cider to the top.", "May also be made in large wine glasses (chill rums and cider first and don't add any ice)."], "category": "Beverages", "similar": [{"id": 243096, "name": "Tokyo Tea"}, {"id": 216763, "name": "Passion Martini"}, {"id": 282170, "name": "Mardi Gras Hurricane 2"}, {"id": 219853, "name": "Nuts and Berries Cocktail"}, {"id": 391716, "name": "Malibu Punch"}]}, {"name": "Cherry Bomb Martini !", "size": 1, "id": 262766, "ingredients": ["Kahlua", "irish cream"], "directions": ["In a cocktail shaker filled with ice add the ingredients and shake till well chilled.", "Pour into a martini glass with or without the ice."], "category": "Beverages", "similar": [{"id": 150063, "name": "Boston Cream Pie Martini"}, {"id": 164176, "name": "Sweet Chocolate Raspberry Martini"}, {"id": 309491, "name": "Chocolate Covered Cherry Martini"}, {"id": 263402, "name": "Wedding Cake Martini II"}, {"id": 457273, "name": "Chocolate Caramel Martini"}]}, {"name": "Wedding Cake Martini II", "size": 1, "id": 263402, "ingredients": ["vanilla vodka", "Amaretto"], "directions": ["Pour all ingredients into a shaker over ice. (orange juice and pineapple juice are just a splash each).", "Shake well.", "Strain into a well chilled martini glass.", "Enjoy! (no smashing into your partners face!)."], "category": "Beverages", "similar": [{"id": 457273, "name": "Chocolate Caramel Martini"}, {"id": 185518, "name": "Madagascar Vanilla Martini"}, {"id": 473113, "name": "Cake Batter Martini"}, {"id": 150063, "name": "Boston Cream Pie Martini"}, {"id": 262766, "name": "Cherry Bomb Martini !"}]}, {"name": "Shark Bite", "size": 1, "id": 263759, "ingredients": ["spiced rum", "blue curacao", "fresh lime juice"], "directions": ["Fill a tall highball or pint glass with ice.", "Add Captain, blue curacao, sour and lime juice.", "Stir with cocktail stirrer or straw.", "Add dash of grenadine to make blood in blue water effect.", "Serve."], "category": "Beverages", "similar": [{"id": 437561, "name": "Liquid Mari-Jane"}, {"id": 391716, "name": "Malibu Punch"}, {"id": 283521, "name": "Pink Mermaid"}, {"id": 262629, "name": "Spicy Sparkling Cider (Cocktail)"}, {"id": 348151, "name": "Pama and Circumstance"}]}, {"name": "Mardi Gras Hurricane 2", "size": 1, "id": 282170, "ingredients": ["amaretto liqueur", "light rum", "dark rum", "lemon juice", "orange", "maraschino cherry"], "directions": ["Fill a 16 ounce glass with ice.", "Pour in amaretto, light rum and dark rum.", "Pour in orange juice, pineapple juice, and lemon juice.", "Stir, then top with a dash of grenadine and garnish with an orange slice and a cherry."], "category": "Beverages", "similar": [{"id": 262629, "name": "Spicy Sparkling Cider (Cocktail)"}, {"id": 216763, "name": "Passion Martini"}, {"id": 243096, "name": "Tokyo Tea"}, {"id": 308145, "name": "Pink Sunset Cocktail"}, {"id": 391716, "name": "Malibu Punch"}]}, {"name": "Pink Mermaid", "size": 1, "id": 283521, "ingredients": ["vodka", "brandy"], "directions": ["Place cream, vodka, crème de almond, and ice cubes in a blender.  Process until the ice is completely crushed and mixture is frothy and light pink.  Pour into a glass and top with brandy."], "category": "Beverages", "similar": [{"id": 391716, "name": "Malibu Punch"}, {"id": 437561, "name": "Liquid Mari-Jane"}, {"id": 216763, "name": "Passion Martini"}, {"id": 291967, "name": "Strawberry Fetish Cocktail"}, {"id": 243096, "name": "Tokyo Tea"}]}, {"name": "Apple Pie and Iced Cream", "size": 1, "id": 284793, "ingredients": ["white cranberry juice", "vanilla vodka"], "directions": ["Shake all ingredients with ice and stain into chilled Martini glass with cinnamon-sugar rim.", "Garnish with an apple slice."], "category": "Beverages", "similar": [{"id": 348151, "name": "Pama and Circumstance"}, {"id": 219677, "name": "Chocolate Milk Shake"}, {"id": 150063, "name": "Boston Cream Pie Martini"}, {"id": 253486, "name": "The Homecoming"}, {"id": 221196, "name": "Pralines and Cream Cocktail"}]}, {"name": "Strawberry Fetish Cocktail", "size": 1, "id": 291967, "ingredients": ["soda water"], "directions": ["Shake all ingredients (except lemonade and soda) and strain into a collins glass filled with broken ice. Add lemonade and soda, garnish with a strawberry, and serve."], "category": "Beverages", "similar": [{"id": 391716, "name": "Malibu Punch"}, {"id": 283521, "name": "Pink Mermaid"}, {"id": 437561, "name": "Liquid Mari-Jane"}, {"id": 216763, "name": "Passion Martini"}, {"id": 219677, "name": "Chocolate Milk Shake"}]}, {"name": "After Eight Shooter", "size": 1, "id": 303712, "ingredients": ["creme de menthe", "Baileys Irish Cream"], "directions": ["Carefully layer the tia maria, creme-de-menthe, and bailey's irish cream, in that order, into a sherry glass, ensuring they don't mix."], "category": "Beverages", "similar": [{"id": 199533, "name": "Buttery Bailey's Nog"}, {"id": 110488, "name": "Nutty Irishman Coffee"}, {"id": 213194, "name": "Skor Bar"}, {"id": 150063, "name": "Boston Cream Pie Martini"}, {"id": 190430, "name": "Oatmeal Cookie Cocktail"}]}, {"name": "Pink Sunset Cocktail", "size": 1, "id": 308145, "ingredients": ["coconut cream", "maraschino cherry juice", "maraschino cherry", "pineapple slice"], "directions": ["Fill cocktail shaker half full with ice. Add first 5 ingredients to shaker. Shake very well. Pour into a hurricane glass and garnish with a maraschino cherry and pineapple slice."], "category": "Beverages", "similar": [{"id": 309491, "name": "Chocolate Covered Cherry Martini"}, {"id": 437561, "name": "Liquid Mari-Jane"}, {"id": 216763, "name": "Passion Martini"}, {"id": 283521, "name": "Pink Mermaid"}, {"id": 243096, "name": "Tokyo Tea"}]}, {"name": "Chocolate Covered Cherry Martini", "size": 1, "id": 309491, "ingredients": ["cherry vodka", "Creme de Cacao", "half-and-half", "maraschino cherry"], "directions": ["Fill a shaker with ice cubes.", "Pour in the chocolate and cherry vodkas, grenadine, creme de cocao, half-and-half, and chocolate syrup. Cover and shake until the outside of the shaker has frosted. Strain into a chilled martini glass, garnish with maraschino cherry and the chocolate kiss, and serve."], "category": "Beverages", "similar": [{"id": 457273, "name": "Chocolate Caramel Martini"}, {"id": 164176, "name": "Sweet Chocolate Raspberry Martini"}, {"id": 185518, "name": "Madagascar Vanilla Martini"}, {"id": 262766, "name": "Cherry Bomb Martini !"}, {"id": 308145, "name": "Pink Sunset Cocktail"}]}, {"name": "Want S'more Martinis?", "size": 1, "id": 314121, "ingredients": ["Baileys Irish Cream", "Creme de Cacao", "vanilla vodka", "heavy cream", "marshmallows", "graham cracker"], "directions": ["Dip the rim of the glass in the chocolate syrup and then in the crushed graham crackers (as you would a margarita with salt). Chill in the freezer.", "Pour all alcohol and heavy cream in a shaker with ice and shake until well blended. Strain into chilled martini glass.", "Add the toasted marshmallows as garnish! YUM!"], "category": "Beverages", "similar": [{"id": 150063, "name": "Boston Cream Pie Martini"}, {"id": 457273, "name": "Chocolate Caramel Martini"}, {"id": 261770, "name": "Cookies &amp; Cream Cocktail"}, {"id": 190430, "name": "Oatmeal Cookie Cocktail"}, {"id": 219677, "name": "Chocolate Milk Shake"}]}, {"name": "Irish Whiskey Cream Liqueur Coffee", "size": 1, "id": 346904, "ingredients": ["espresso coffee", "irish cream", "sugar", "milk", "ground cinnamon", "nutmeg"], "directions": ["Make the espresso and pour in the liqueur. Stir in the sugar.", "Pour in the hot milk, sprinkle over the ground spices and serve at once."], "category": "Beverages", "similar": [{"id": 184346, "name": "Nutty Irishman Coffee With a Kick!!!!"}, {"id": 110488, "name": "Nutty Irishman Coffee"}, {"id": 407442, "name": "Chocolatey Irish Coffee"}, {"id": 216594, "name": "Irish Flag Layered Shot"}, {"id": 216596, "name": "Irish Sunset/Sunrise"}]}, {"name": "Pama and Circumstance", "size": 1, "id": 348151, "ingredients": ["vodka", "cranberry juice"], "directions": ["Shake all ingredients together in a shakerof ice.", "Pour into a martini glass rimmed with sugar and garnish with a slice of star fruit and a mint sprig ( if you like).", "ENJOY!"], "category": "Beverages", "similar": [{"id": 355188, "name": "The Love Potion"}, {"id": 284793, "name": "Apple Pie and Iced Cream"}, {"id": 437561, "name": "Liquid Mari-Jane"}, {"id": 253486, "name": "The Homecoming"}, {"id": 391716, "name": "Malibu Punch"}]}, {"name": "Coffee Ice Cream Soda, Hold the Soda!", "size": 1, "id": 352449, "ingredients": ["coffee", "vanilla ice cream", "chocolate ice cream"], "directions": ["Use two 16 ounce mugs or glasses for this treat.", "Pour 8 ounces of coffee in each glass.", "Stir in 2 tablespoons of non-dairy creamer in each glass.", "Stir 1 tablespoon chocolate syrup in each glass.", "Add 4 ounces of ice cream to each glass.", "Top with whip cream (optional).", "Makes two 16 ounce drinks. Enjoy!"], "category": "Beverages", "similar": [{"id": 219677, "name": "Chocolate Milk Shake"}, {"id": 291967, "name": "Strawberry Fetish Cocktail"}, {"id": 261770, "name": "Cookies &amp; Cream Cocktail"}, {"id": 284793, "name": "Apple Pie and Iced Cream"}, {"id": 437561, "name": "Liquid Mari-Jane"}]}, {"name": "The Love Potion", "size": 1, "id": 355188, "ingredients": ["vodka", "Amaretto", "cranberry juice", "cranberries", "raspberries"], "directions": ["Combine liquors and ice in a cocktail shaker. Shake until the shaker is well-covered in condensation. Serve on the rocks, or up in a martini glass. Garnish with cranberries or raspberries."], "category": "Beverages", "similar": [{"id": 253486, "name": "The Homecoming"}, {"id": 348151, "name": "Pama and Circumstance"}, {"id": 284793, "name": "Apple Pie and Iced Cream"}, {"id": 391716, "name": "Malibu Punch"}, {"id": 216763, "name": "Passion Martini"}]}, {"name": "Malibu Punch", "size": 1, "id": 391716, "ingredients": ["raspberry vodka", "Amaretto"], "directions": ["Mix all and serve over ice.", "Garnish with Oranfge juice and/ or Cherry."], "category": "Beverages", "similar": [{"id": 216763, "name": "Passion Martini"}, {"id": 245853, "name": "Absolut Iced Tea"}, {"id": 243096, "name": "Tokyo Tea"}, {"id": 437561, "name": "Liquid Mari-Jane"}, {"id": 283521, "name": "Pink Mermaid"}]}, {"name": "Chocolatey Irish Coffee", "size": 1, "id": 407442, "ingredients": ["Baileys Irish Cream", "Creme de Cacao"], "directions": ["Pour all of the ingredients into your favourite mug, stir and enjoy!"], "category": "Beverages", "similar": [{"id": 184346, "name": "Nutty Irishman Coffee With a Kick!!!!"}, {"id": 110488, "name": "Nutty Irishman Coffee"}, {"id": 346904, "name": "Irish Whiskey Cream Liqueur Coffee"}, {"id": 199533, "name": "Buttery Bailey's Nog"}, {"id": 190430, "name": "Oatmeal Cookie Cocktail"}]}, {"name": "Liquid Mari-Jane", "size": 1, "id": 437561, "ingredients": ["blue curacao", "lime wedge"], "directions": ["Add Melon Liqueur, Blue Curacao, Peach Schnapps, Coconut Rum, and Southern Comfort to ice in Shaker. Pour in Orange Juice and Pineapple Juice. Squeeze Lime wedge.", "Shake until well mixed. Should come out as an Herbal Green color.", "Pour into Pint Glass.", "Garnish with Lime and Cherry.", "Enjoy Responsibly."], "category": "Beverages", "similar": [{"id": 263759, "name": "Shark Bite"}, {"id": 391716, "name": "Malibu Punch"}, {"id": 283521, "name": "Pink Mermaid"}, {"id": 216763, "name": "Passion Martini"}, {"id": 348151, "name": "Pama and Circumstance"}]}, {"name": "Chocolate Caramel Martini", "size": 1, "id": 457273, "ingredients": ["vanilla vodka"], "directions": ["Swirl Somebody's Mother's Caramel Sauce around the inside rim of a martini glass.", "Fill shaker with ice. Pour in ingredients.", "Shake well and pour into the martini glass.", "If done correctly, it should taste like an adult milkshake.", "A little whipped cream on top never hurt anyone either!"], "category": "Beverages", "similar": [{"id": 164176, "name": "Sweet Chocolate Raspberry Martini"}, {"id": 309491, "name": "Chocolate Covered Cherry Martini"}, {"id": 263402, "name": "Wedding Cake Martini II"}, {"id": 473113, "name": "Cake Batter Martini"}, {"id": 185518, "name": "Madagascar Vanilla Martini"}]}, {"name": "Whoopie Pie Martini", "size": 1, "id": 473112, "ingredients": ["vodka"], "directions": ["Combine ingredients in a shaker with ice.", "Shake and strain into a martini glass to serve."], "category": "Beverages", "similar": [{"id": 473113, "name": "Cake Batter Martini"}, {"id": 150063, "name": "Boston Cream Pie Martini"}, {"id": 457273, "name": "Chocolate Caramel Martini"}, {"id": 164176, "name": "Sweet Chocolate Raspberry Martini"}, {"id": 263402, "name": "Wedding Cake Martini II"}]}, {"name": "Cake Batter Martini", "size": 1, "id": 473113, "ingredients": ["vodka"], "directions": ["Combine ingredients in a shaker with ice.", "Shake and strain into a martini glass.", "Garnish with whipped cream and white chocolate shavings."], "category": "Beverages", "similar": [{"id": 473112, "name": "Whoopie Pie Martini"}, {"id": 457273, "name": "Chocolate Caramel Martini"}, {"id": 164176, "name": "Sweet Chocolate Raspberry Martini"}, {"id": 263402, "name": "Wedding Cake Martini II"}, {"id": 150063, "name": "Boston Cream Pie Martini"}]}, {"name": "Purple Dream", "size": 1, "id": 483263, "ingredients": ["Chambord raspberry liquor", "white Creme de Cacao"], "directions": ["Pour ingredients into a cocktail shaker filled with ice.", "Shake until completely cold then strain into a chilled stemmed glass or a rocks glass filled with ice."], "category": "Beverages", "similar": [{"id": 189425, "name": "White Chocolate Raspberry Truffle"}, {"id": 185515, "name": "African Raspberry"}, {"id": 437561, "name": "Liquid Mari-Jane"}, {"id": 263759, "name": "Shark Bite"}, {"id": 213194, "name": "Skor Bar"}]}]