[{"name": "Pesto", "size": 1, "id": 13044, "ingredients": ["pine nuts", "garlic", "salt", "fresh basil", "parmesan cheese", "olive oil"], "directions": ["Lightly toast pine nuts.", "In a food processor (or with a pestle and mortar), mix the basil, garlic, pine nuts and cheese into a paste.", "Add oil and blend to a smooth paste.", "Keep in an airtight jar in the fridge."], "category": "Sauces", "similar": [{"id": 121569, "name": "Pesto Sauce"}, {"id": 506242, "name": "Carrot Greens Pesto"}, {"id": 266866, "name": "Presto Pesto"}, {"id": 317262, "name": "Classic Pesto"}, {"id": 266572, "name": "Sicilian Tomato Pesto"}]}, {"name": "Pesto Sauce", "size": 1, "id": 121569, "ingredients": ["fresh basil leaves", "pine nuts", "garlic cloves", "parmesan cheese", "coarse salt"], "directions": ["Directions:", "Combine first 4 ingredients in blender. Blend until paste forms, stopping often to push down basil. Add both cheeses and salt; blend until smooth. Transfer to small bowl. (Can be made 1 day ahead. Top with 1/2 inch olive oil and chill.) Makes about 1 cup.", "To freeze: divide into small portions.", "Some people freeze in ice cube trays."], "category": "Sauces", "similar": [{"id": 13044, "name": "Pesto"}, {"id": 484401, "name": "Garlic-Free Parsley Pesto"}, {"id": 317262, "name": "Classic Pesto"}, {"id": 266866, "name": "Presto Pesto"}, {"id": 506242, "name": "Carrot Greens Pesto"}]}, {"name": "Parsley Pesto With Toasted Walnuts", "size": 1, "id": 254340, "ingredients": ["Italian parsley", "fresh basil leaf", "walnuts", "parmesan cheese", "garlic clove", "low sodium chicken broth", "olive oil", "olive oil"], "directions": ["Combine parsley, basil, walnuts Parmesan cheese and garlic in processor. Process until mixture is finely chopped.", "Add chicken broth and puree. With machine running, gradually add oil and process until mixture is smooth.", "Transfer to large bowl. Season with salt and pepper.", "Note: this may be prepared 2 hours in advance."], "category": "Sauces", "similar": [{"id": 317262, "name": "Classic Pesto"}, {"id": 357625, "name": "Pesto (Vita-Mix or Blender)"}, {"id": 484401, "name": "Garlic-Free Parsley Pesto"}, {"id": 506242, "name": "Carrot Greens Pesto"}, {"id": 13044, "name": "Pesto"}]}, {"name": "Spinach - Arugula Pesto", "size": 1, "id": 255857, "ingredients": ["garlic cloves", "lemon rind", "crushed red pepper flakes", "arugula leaves", "pine nuts", "fresh lemon juice", "olive oil", "parmesan cheese", "sea salt"], "directions": ["Microwave spinach, uncovered, on high heat until just wilted (about 1 1/2 minutes).  Drain, then squeeze out as much liquid as possible.", "Combine the garlic, lemon peel, and crushed red pepper in processor and blend until garlic is finely chopped.", "Add spinach and arugula, pine nuts, and lemon juice: process until coarse puree forms.", "With the machine running, gradually add the oil in a thin stream and blend until almost smooth.", "Add the cheese and blend to mix.", "Season with salt. Cover and chill.", "Serve on burgers or sandwiches."], "category": "Sauces", "similar": [{"id": 317262, "name": "Classic Pesto"}, {"id": 357625, "name": "Pesto (Vita-Mix or Blender)"}, {"id": 366643, "name": "Sorrel Pesto"}, {"id": 387405, "name": "Fantastically Healthy Pesto"}, {"id": 299637, "name": "Arugula Pesto."}]}, {"name": "Sicilian Tomato Pesto", "size": 1, "id": 266572, "ingredients": ["pine nuts", "fresh basil leaves", "garlic cloves", "extra virgin olive oil", "parmigiano-reggiano cheese", "red pepper flakes", "tomatoes"], "directions": ["Heat a small skillet over medium-high heat and add the pine nuts.", "Cook, stirring constantly, until golden, 3 to 4 minutes. Immediately remove from the pan.", "Place the basil leaves, garlic, pine nuts and olive oil in a blender or food processor and process until smooth.", "Stop and scrape down the sides.", "Add the grated cheese and crushed red-pepper flakes and pulse a few times to make a thick paste.", "Transfer to a bowl and fold in the tomatoes. Season with salt and pepper."], "category": "Sauces", "similar": [{"id": 317262, "name": "Classic Pesto"}, {"id": 13044, "name": "Pesto"}, {"id": 266866, "name": "Presto Pesto"}, {"id": 121569, "name": "Pesto Sauce"}, {"id": 357625, "name": "Pesto (Vita-Mix or Blender)"}]}, {"name": "Presto Pesto", "size": 1, "id": 266866, "ingredients": ["garlic clove", "pine nuts", "fresh basil", "parmesan cheese", "olive oil", "salt"], "directions": ["In a food processor blend together the nuts, garlic and salt to a paste.", "Add the basil and begin blending while simultaneously slowly drizzling in the oil.", "Stir in the cheese by hand in the bowl with which you plan to serve the sauce inches.", "Bon Apetite!", "NOTE- walnuts can be substituted for the pine nuts."], "category": "Sauces", "similar": [{"id": 13044, "name": "Pesto"}, {"id": 121569, "name": "Pesto Sauce"}, {"id": 266572, "name": "Sicilian Tomato Pesto"}, {"id": 317262, "name": "Classic Pesto"}, {"id": 367149, "name": "The Realtor's Pesto"}]}, {"name": "Arugula Pesto.", "size": 1, "id": 299637, "ingredients": ["sunflower seeds", "arugula", "olive oil", "fresh lemon juice", "garlic cloves", "salt", "pepper"], "directions": ["Toast sunflower seeds in dry skillet 5 minutes.", "Transfer to food processor.", "Add arugula, olive oil, lemon juice, and garlic, and process until smooth.", "Season with salt and pepper."], "category": "Sauces", "similar": [{"id": 364574, "name": "Arugula Pesto"}, {"id": 444801, "name": "Kale-Almond Pesto"}, {"id": 366643, "name": "Sorrel Pesto"}, {"id": 387405, "name": "Fantastically Healthy Pesto"}, {"id": 536864, "name": "Beet Greens Pesto"}]}, {"name": "Classic Pesto", "size": 1, "id": 317262, "ingredients": ["fresh basil", "flat leaf parsley", "pine nuts", "garlic cloves", "parmesan cheese", "extra virgin olive oil"], "directions": ["Combine and whirl basil, parsley, pine nuts and garlic in a food processor until chopped.", "Add cheese gradually pour in oil processing until smooth.", "Add salt and pepper to taste.", "Transfer to a small bowl and cover in plastic wrap, pressing the wrap on to the surface to prevent browning.", "Use within a week or freeze."], "category": "Sauces", "similar": [{"id": 357625, "name": "Pesto (Vita-Mix or Blender)"}, {"id": 506242, "name": "Carrot Greens Pesto"}, {"id": 254340, "name": "Parsley Pesto With Toasted Walnuts"}, {"id": 367149, "name": "The Realtor's Pesto"}, {"id": 13044, "name": "Pesto"}]}, {"name": "Pesto (Vita-Mix or Blender)", "size": 1, "id": 357625, "ingredients": ["olive oil", "garlic cloves", "pine nuts", "parmesan cheese", "basil leaves"], "directions": ["add ingredients to Vita-Mix (or other blender) in the order displayed.", "turn machine to Variable Speed 1, then increase quickly to Variable Speed 7.", "blend for 1 minute.", "serve immediately or store in fridge.", "to avoid discoloration of the top, pour a thin layer of olive oil on the top of the pesto."], "category": "Sauces", "similar": [{"id": 317262, "name": "Classic Pesto"}, {"id": 506242, "name": "Carrot Greens Pesto"}, {"id": 444801, "name": "Kale-Almond Pesto"}, {"id": 254340, "name": "Parsley Pesto With Toasted Walnuts"}, {"id": 13044, "name": "Pesto"}]}, {"name": "Arugula Pesto", "size": 1, "id": 364574, "ingredients": ["sunflower seeds", "arugula", "olive oil", "fresh lemon juice", "garlic cloves"], "directions": ["Toast sunflower seeds in dry skillet 3 minutes, or until lightly browned. Transfer to food processor.", "Add arugula, olive oil, lemon juice, and garlic, and process until smooth. Season with salt and pepper."], "category": "Sauces", "similar": [{"id": 299637, "name": "Arugula Pesto."}, {"id": 444801, "name": "Kale-Almond Pesto"}, {"id": 387405, "name": "Fantastically Healthy Pesto"}, {"id": 536864, "name": "Beet Greens Pesto"}, {"id": 366643, "name": "Sorrel Pesto"}]}, {"name": "Sorrel Pesto", "size": 1, "id": 366643, "ingredients": ["fresh sorrel", "fresh parsley leaves", "garlic cloves", "parmesan cheese", "pine nuts", "salt", "olive oil"], "directions": ["In a food processor or blender puree the sorrel, the parsley, the garlic, the parmesan, the pine nuts and the oil, transfer the pesto to a jar with a tight fitting lid and chill it, covered. The pesto keeps, covered and chilled, for 2 weeks. Makes about 1 cup.", "To use the pesto: For every pound of dried pasta cooking in a kettle of boiling water, stir together in a heated serving bowl 3/4 cup of the pesto and 2/3 cup of the hot cooking water. When the pasta is al dente, drain it in a colander, add it to the pesto mixture, and toss the mixture until the pasta is coated well. Vermicelli works very well with this recipe."], "category": "Sauces", "similar": [{"id": 299637, "name": "Arugula Pesto."}, {"id": 317262, "name": "Classic Pesto"}, {"id": 444801, "name": "Kale-Almond Pesto"}, {"id": 536864, "name": "Beet Greens Pesto"}, {"id": 255857, "name": "Spinach - Arugula Pesto"}]}, {"name": "The Realtor's Pesto", "size": 1, "id": 367149, "ingredients": ["fresh basil leaves", "olive oil", "romano cheese", "fresh parsley leaves", "pine nuts", "garlic cloves"], "directions": ["Place all ingredients in food processor bowl and process using metal blade until finely chopped but not mushy.", "Spoon into jar and cover with a thin layer of olive oil to prevent the mixture from darkening.", "Refrigerate for at least 2 hours so flavors can blend or up to 2 weeks.", "To freeze, put tablespoonfuls of the pesto mixture into ice cube trays. freeze and pop them out as needed.  I keep the whole ice cube tray in a big ziploc bag to keep the pesto cubes fresh.  You could pop them out and store them in the bag without the tray but I've found that they stick together too much.", "I use about 1/3 of a cup or so per pound of pasta and 1 or 2 cubes per 1lb of roasted or steamed veggies."], "category": "Sauces", "similar": [{"id": 317262, "name": "Classic Pesto"}, {"id": 266866, "name": "Presto Pesto"}, {"id": 121569, "name": "Pesto Sauce"}, {"id": 13044, "name": "Pesto"}, {"id": 266572, "name": "Sicilian Tomato Pesto"}]}, {"name": "Fantastically Healthy Pesto", "size": 1, "id": 387405, "ingredients": ["garlic cloves", "miso", "white wine vinegar", "nutritional yeast", "olive oil"], "directions": ["In your food processor, place the almonds and garlic cloves. Chop until a course grind is achieved.", "Add spinach by the handful and continue to work until a paste forms.", "Add miso, white wine vinegar and nutritional yeast.", "Stream in olive oil while processor runs until desired consistency is achieved.", "Season with salt and pepper as desired.", "Serve immediately or warmed over any pasta."], "category": "Sauces", "similar": [{"id": 536864, "name": "Beet Greens Pesto"}, {"id": 299637, "name": "Arugula Pesto."}, {"id": 364574, "name": "Arugula Pesto"}, {"id": 366643, "name": "Sorrel Pesto"}, {"id": 317262, "name": "Classic Pesto"}]}, {"name": "Kale-Almond Pesto", "size": 1, "id": 444801, "ingredients": ["kale", "shallots", "garlic clove", "parmigiano-reggiano cheese", "olive oil"], "directions": ["Steam  the kale  for 10 minutes and let cool.", "Place kale, almonds, shallots, garlic, cheese. salt and pepper in a food processor.", "Pulse several times to combine then drizzle in the oil as you continue to mix.", "Adjust seasoning as needed."], "category": "Sauces", "similar": [{"id": 299637, "name": "Arugula Pesto."}, {"id": 357625, "name": "Pesto (Vita-Mix or Blender)"}, {"id": 364574, "name": "Arugula Pesto"}, {"id": 366643, "name": "Sorrel Pesto"}, {"id": 536864, "name": "Beet Greens Pesto"}]}, {"name": "Garlic-Free Parsley Pesto", "size": 1, "id": 484401, "ingredients": ["parsley", "salt", "shallot", "olive oil", "walnut halves", "lemon juice", "parmesan cheese"], "directions": ["Clean and remove big stems from parsley.", "In a food processor or magic bullet put the parsley, salt, walnuts, shallot and half the oil.", "Blend until pureed.", "Add remaining oil, lemon juice and parmesan and blend quickly."], "category": "Sauces", "similar": [{"id": 121569, "name": "Pesto Sauce"}, {"id": 13044, "name": "Pesto"}, {"id": 506242, "name": "Carrot Greens Pesto"}, {"id": 317262, "name": "Classic Pesto"}, {"id": 254340, "name": "Parsley Pesto With Toasted Walnuts"}]}, {"name": "Carrot Greens Pesto", "size": 1, "id": 506242, "ingredients": ["garlic clove", "pine nuts", "basil leaves", "parmesan cheese", "extra virgin olive oil"], "directions": ["Pulse garlic and nuts in a food processor until a coarse paste forms.", "Add carrot greens, basil and Parmesan; process until a coarse puree forms.", "Add enough olive oil to make the paste smooth; season with salt and pepper."], "category": "Sauces", "similar": [{"id": 13044, "name": "Pesto"}, {"id": 317262, "name": "Classic Pesto"}, {"id": 357625, "name": "Pesto (Vita-Mix or Blender)"}, {"id": 121569, "name": "Pesto Sauce"}, {"id": 484401, "name": "Garlic-Free Parsley Pesto"}]}, {"name": "Beet Greens Pesto", "size": 1, "id": 536864, "ingredients": ["walnuts", "parmesan cheese", "salt", "fresh cracked pepper", "garlic cloves", "extra virgin olive oil"], "directions": ["Place all ingredients EXCEPT OIL in the food processor or blender. Pulse a few times then process on high until everything is combined but do not puree it.", "While the blender is working, pour in the olive oil slowly until the texture is of your pesto liking.", "Use as is for all pesto applications or store in air tight container for up to a week or so. Not suitable to freeze."], "category": "Sauces", "similar": [{"id": 387405, "name": "Fantastically Healthy Pesto"}, {"id": 506242, "name": "Carrot Greens Pesto"}, {"id": 366643, "name": "Sorrel Pesto"}, {"id": 444801, "name": "Kale-Almond Pesto"}, {"id": 299637, "name": "Arugula Pesto."}]}]